fc_audit/__init__.py
fc_audit/__main__.py
fc_audit/alias_outputter.py
fc_audit/cli.py
fc_audit/exceptions.py
fc_audit/fcstd.py
fc_audit/logging.py
fc_audit/parser.py
fc_audit/properties_outputter.py
fc_audit/py.typed
fc_audit/reference.py
fc_audit/reference_collector.py
fc_audit/reference_outputter.py
fc_audit/validation.py
fc_audit/version.py
fc_audit-0.1.4.dist-info/METADATA
fc_audit-0.1.4.dist-info/WHEEL
fc_audit-0.1.4.dist-info/entry_points.txt
fc_audit-0.1.4.dist-info/RECORD
