Metadata-Version: 2.4
Name: fc-audit
Version: 0.1.4
Summary: Command line audit tool
Project-URL: fc-audit, https://github.com/royw/fc-audit
Author-email: Roy Wright <roy@wright.org>
Maintainer-email: Roy Wright <roy@wright.org>
License: MIT License
Keywords: CLI,FreeCAD,python
Classifier: Development Status :: 2 - Pre-Alpha
Classifier: Environment :: Console
Classifier: Intended Audience :: Developers
Classifier: License :: OSI Approved :: MIT License
Classifier: Natural Language :: English
Classifier: Operating System :: POSIX :: Linux
Classifier: Programming Language :: Python :: 3
Classifier: Topic :: Multimedia :: Graphics :: 3D Modeling
Requires-Python: >=3.11
Requires-Dist: loguru>=0.7.2
Requires-Dist: lxml>=5.1.0
Provides-Extra: dev
Requires-Dist: build>=1.1.0; extra == 'dev'
Requires-Dist: codespell>=2.2.6; extra == 'dev'
Requires-Dist: deadcode>=1.1.0; extra == 'dev'
Requires-Dist: lxml-stubs>=0.5.1; extra == 'dev'
Requires-Dist: mkdocs-material>=9.5.0; extra == 'dev'
Requires-Dist: mkdocs>=1.5.0; extra == 'dev'
Requires-Dist: mkdocstrings-python>=1.8.0; extra == 'dev'
Requires-Dist: mkdocstrings>=0.24.0; extra == 'dev'
Requires-Dist: mypy>=1.15.0; extra == 'dev'
Requires-Dist: pre-commit>=3.6.0; extra == 'dev'
Requires-Dist: pytest-cov>=4.1.0; extra == 'dev'
Requires-Dist: pytest-mock>=3.12.0; extra == 'dev'
Requires-Dist: pytest-mypy>=0.10.3; extra == 'dev'
Requires-Dist: pytest>=8.0.0; extra == 'dev'
Requires-Dist: radon>=6.0.1; extra == 'dev'
Requires-Dist: ruff>=0.11.5; extra == 'dev'
Requires-Dist: toml-cli>=0.7.0; extra == 'dev'
Requires-Dist: tox>=4.25.0; extra == 'dev'
Requires-Dist: twine>=5.0.0; extra == 'dev'
Requires-Dist: version-bumper<0.2.0,>=0.1.1; extra == 'dev'
